log_enricher/__init__.py
log_enricher/enrichers.py
log_enricher-2.1.1.dist-info/METADATA
log_enricher-2.1.1.dist-info/WHEEL
log_enricher-2.1.1.dist-info/RECORD
