Metadata-Version: 2.1
Name: log-enricher
Version: 2.1.1
Summary: Library to enrich structured logs
Home-page: https://github.com/arni-inaba/log-enricher
License: MIT
Author: Arni Inaba Kjartansson
Author-email: arni@grid.is
Requires-Python: >=3.8,<4.0
Classifier: License :: OSI Approved :: MIT License
Classifier: Programming Language :: Python :: 3
Classifier: Programming Language :: Python :: 3.8
Classifier: Programming Language :: Python :: 3.9
Classifier: Programming Language :: Python :: 3.10
Classifier: Programming Language :: Python :: 3.11
Classifier: Programming Language :: Python :: 3.12
Requires-Dist: python-json-logger (>=2.0.4,<3.0.0)
Requires-Dist: strenum (>=0.4.0,<0.5.0)
Project-URL: Repository, https://github.com/arni-inaba/log-enricher
